setup.py
shlex.py
micropython_shlex.egg-info/PKG-INFO
micropython_shlex.egg-info/SOURCES.txt
micropython_shlex.egg-info/dependency_links.txt
micropython_shlex.egg-info/top_level.txt