Metadata-Version: 1.0
Name: micropython-shlex
Version: 0.0.1
Summary: Dummy shlex module for MicroPython
Home-page: https://github.com/micropython/micropython/issues/405
Author: MicroPython Developers
Author-email: micro-python@googlegroups.com
License: MIT
Platform: UNKNOWN
